<annotation>
	<folder>images</folder>
	<filename>dutch-rose-500x500.jpeg</filename>
	<path>C:\Users\PK\Desktop\images\images\dutch-rose-500x500.jpeg</path>
	<source>
		<database>Unknown</database>
	</source>
	<size>
		<width>500</width>
		<height>500</height>
		<depth>3</depth>
	</size>
	<segmented>0</segmented>
	<object>
		<name>rose</name>
		<pose>Unspecified</pose>
		<truncated>0</truncated>
		<difficult>0</difficult>
		<bndbox>
			<xmin>113</xmin>
			<ymin>40</ymin>
			<xmax>388</xmax>
			<ymax>282</ymax>
		</bndbox>
	</object>
</annotation>
